crawl2md/__init__.py
crawl2md/cli.py
crawl2md/config.py
crawl2md/crawler.py
crawl2md/theme.py
crawl2md/tui.py
crawl2md-0.1.0.dist-info/METADATA
crawl2md-0.1.0.dist-info/WHEEL
crawl2md-0.1.0.dist-info/entry_points.txt
crawl2md-0.1.0.dist-info/top_level.txt
crawl2md-0.1.0.dist-info/RECORD
